[
  {
    "id": "tylenol_susp_100ml_kr",
    "name": "어린이 타이레놀 현탁액 100mL",
    "image_url": null,
    "needs_manual_image": true
  },
  {
    "id": "champ_syrup_red_kr",
    "name": "챔프 시럽 (빨강)",
    "image_url": null,
    "needs_manual_image": true
  },
  {
    "id": "tylenol_susp_200ml_kr",
    "name": "어린이 타이레놀 현탁액 200mL",
    "image_url": null,
    "needs_manual_image": true
  },
  {
    "id": "brufen_susp_100_5_kr",
    "name": "어린이 부루펜 시럽",
    "image_url": null,
    "needs_manual_image": true
  },
  {
    "id": "maxibufen_susp_12_1_kr",
    "name": "맥시부펜 시럽",
    "image_url": null,
    "needs_manual_image": true
  }
]